{
  "metadata": {
    "bookTitle": "songs_index.json",
    "category": "Partitions",
    "style": "Funk",
    "totalPages": 120,
    "processedDate": "2025-11-12T21:31:15.208Z"
  },
  "content": {
    "songs": [
      {
        "title": "Love's In Need Of Love Today",
        "page": 10,
        "style": "Soul",
        "category": "Partitions"
      },
      {
        "title": "Have A Talk With God",
        "page": 15,
        "style": "Soul",
        "category": "Partitions"
      },
      {
        "title": "Village Ghetto Land",
        "page": 19,
        "style": "Soul",
        "category": "Partitions"
      },
      {
        "title": "Village Ghetto Land",
        "page": 19,
        "style": "Soul",
        "category": "Partitions"
      },
      {
        "title": "Confusion",
        "page": 22,
        "style": "Jazz Rock",
        "category": "Partitions"
      },
      {
        "title": "Sir Duke",
        "page": 25,
        "style": "Soul",
        "category": "Partitions"
      },
      {
        "title": "I Wish",
        "page": 28,
        "style": "Soul",
        "category": "Partitions"
      },
      {
        "title": "Knocks Me Off My Feet",
        "page": 36,
        "style": "Soul",
        "category": "Partitions"
      },
      {
        "title": "Pastime Paradise",
        "page": 42,
        "style": "Soul",
        "category": "Partitions"
      },
      {
        "title": "Summer Soft",
        "page": 46,
        "style": "Soul",
        "category": "Partitions"
      },
      {
        "title": "Ordinary Pain",
        "page": 52,
        "style": "Soul",
        "category": "Partitions"
      },
      {
        "title": "Isn't She Lovely",
        "page": 58,
        "style": "Soul",
        "category": "Partitions"
      },
      {
        "title": "Isn't She Lovely",
        "page": 59,
        "style": "Soul/R&B",
        "category": "Partitions"
      },
      {
        "title": "Joy Inside My Tears",
        "page": 61,
        "style": "Soul/Ballad",
        "category": "Partitions"
      },
      {
        "title": "Black Man",
        "page": 66,
        "style": "Funk/Soul",
        "category": "Partitions"
      },
      {
        "title": "Ngiculela - Es Una Historia - I Am Singing",
        "page": 74,
        "style": "World/Soul",
        "category": "Partitions"
      },
      {
        "title": "Ngiculela (continuation)",
        "page": 79,
        "style": "World/Soul",
        "category": "Partitions"
      },
      {
        "title": "Ngiculela (continuation)",
        "page": 80,
        "style": "World/Soul",
        "category": "Partitions"
      },
      {
        "title": "If It's Magic",
        "page": 82,
        "style": "Ballad/Soul",
        "category": "Partitions"
      },
      {
        "title": "As",
        "page": 88,
        "style": "Funk/Rock",
        "category": "Partitions"
      },
      {
        "title": "Another Star",
        "page": 96,
        "style": "Calypso/Funk",
        "category": "Partitions"
      },
      {
        "title": "Saturn",
        "page": 100,
        "style": "Ballad/Soul",
        "category": "Partitions"
      },
      {
        "title": "Saturn (continuation)",
        "page": 101,
        "style": "Ballad/Soul",
        "category": "Partitions"
      },
      {
        "title": "Ebony Eyes",
        "page": 106,
        "style": "Soul/Ballad",
        "category": "Partitions"
      },
      {
        "title": "All Day Sucker",
        "page": 110,
        "style": "Funk/Soul",
        "category": "Partitions"
      },
      {
        "title": "Easy Goin' Evening (Mo Mama's Call)",
        "page": 114,
        "style": "Jazz/Swing",
        "category": "Partitions"
      }
    ],
    "exercises": [],
    "concepts": []
  }
}